LICENSE
MANIFEST.in
README.rst
requirements.txt
setup.cfg
setup.py
modoboa_admin_limits/__init__.py
modoboa_admin_limits/app_settings.py
modoboa_admin_limits/controls.py
modoboa_admin_limits/forms.py
modoboa_admin_limits/general_callbacks.py
modoboa_admin_limits/lib.py
modoboa_admin_limits/models.py
modoboa_admin_limits/modo_extension.py
modoboa_admin_limits/tests.py
modoboa_admin_limits/urls.py
modoboa_admin_limits/views.py
modoboa_admin_limits.egg-info/PKG-INFO
modoboa_admin_limits.egg-info/SOURCES.txt
modoboa_admin_limits.egg-info/dependency_links.txt
modoboa_admin_limits.egg-info/not-zip-safe
modoboa_admin_limits.egg-info/requires.txt
modoboa_admin_limits.egg-info/top_level.txt
modoboa_admin_limits/locale/cs_CZ/LC_MESSAGES/django.mo
modoboa_admin_limits/locale/cs_CZ/LC_MESSAGES/django.po
modoboa_admin_limits/locale/de/LC_MESSAGES/django.mo
modoboa_admin_limits/locale/de/LC_MESSAGES/django.po
modoboa_admin_limits/locale/en/LC_MESSAGES/django.mo
modoboa_admin_limits/locale/en/LC_MESSAGES/django.po
modoboa_admin_limits/locale/es/LC_MESSAGES/django.mo
modoboa_admin_limits/locale/es/LC_MESSAGES/django.po
modoboa_admin_limits/locale/fr/LC_MESSAGES/django.mo
modoboa_admin_limits/locale/fr/LC_MESSAGES/django.po
modoboa_admin_limits/locale/it/LC_MESSAGES/django.mo
modoboa_admin_limits/locale/it/LC_MESSAGES/django.po
modoboa_admin_limits/locale/nl_NL/LC_MESSAGES/django.mo
modoboa_admin_limits/locale/nl_NL/LC_MESSAGES/django.po
modoboa_admin_limits/locale/pt_BR/LC_MESSAGES/django.mo
modoboa_admin_limits/locale/pt_BR/LC_MESSAGES/django.po
modoboa_admin_limits/locale/pt_PT/LC_MESSAGES/django.mo
modoboa_admin_limits/locale/pt_PT/LC_MESSAGES/django.po
modoboa_admin_limits/locale/ru/LC_MESSAGES/django.mo
modoboa_admin_limits/locale/ru/LC_MESSAGES/django.po
modoboa_admin_limits/locale/sv/LC_MESSAGES/django.mo
modoboa_admin_limits/locale/sv/LC_MESSAGES/django.po
modoboa_admin_limits/migrations/0001_initial.py
modoboa_admin_limits/migrations/__init__.py
modoboa_admin_limits/templates/modoboa_admin_limits/poolusage.html